xia_connector_sendinblue/__init__.py
xia_connector_sendinblue/connector.cpython-310-darwin.so
xia_connector_sendinblue-0.0.1.dist-info/LICENSE.txt
xia_connector_sendinblue-0.0.1.dist-info/METADATA
xia_connector_sendinblue-0.0.1.dist-info/WHEEL
xia_connector_sendinblue-0.0.1.dist-info/top_level.txt
xia_connector_sendinblue-0.0.1.dist-info/RECORD
