Metadata-Version: 2.1
Name: xia-connector-sendinblue
Version: 0.0.1
Summary: X-I-A
Home-page: https://develop.x-i-a.com/docs/xia-connector-sendinblue/0.0.1/index.html
Author: X-I-A
Author-email: admin@x-i-a.com
Requires-Python: >=3.7
License-File: LICENSE.txt
Requires-Dist: requests
Requires-Dist: xia-connector-mail
